odoo10_addon_github_connector_odoo-10.0.1.0.0.99.dev5-py2.7-nspkg.pth
odoo/addons/github_connector_odoo/README.rst
odoo/addons/github_connector_odoo/__init__.py
odoo/addons/github_connector_odoo/__openerp__.py
odoo/addons/github_connector_odoo/data/function.xml
odoo/addons/github_connector_odoo/data/odoo_licence.xml
odoo/addons/github_connector_odoo/demo/github_organization.xml
odoo/addons/github_connector_odoo/models/__init__.py
odoo/addons/github_connector_odoo/models/github_organization.py
odoo/addons/github_connector_odoo/models/github_repository.py
odoo/addons/github_connector_odoo/models/github_repository_branch.py
odoo/addons/github_connector_odoo/models/odoo_author.py
odoo/addons/github_connector_odoo/models/odoo_lib_bin.py
odoo/addons/github_connector_odoo/models/odoo_lib_python.py
odoo/addons/github_connector_odoo/models/odoo_license.py
odoo/addons/github_connector_odoo/models/odoo_module.py
odoo/addons/github_connector_odoo/models/odoo_module_version.py
odoo/addons/github_connector_odoo/security/ir.model.access.csv
odoo/addons/github_connector_odoo/static/description/github_organization_form.png
odoo/addons/github_connector_odoo/static/description/icon.png
odoo/addons/github_connector_odoo/static/description/menu.png
odoo/addons/github_connector_odoo/static/description/odoo_author.png
odoo/addons/github_connector_odoo/static/description/odoo_bin_libs.png
odoo/addons/github_connector_odoo/static/description/odoo_license.png
odoo/addons/github_connector_odoo/static/description/odoo_module_form.png
odoo/addons/github_connector_odoo/static/description/odoo_module_kanban.png
odoo/addons/github_connector_odoo/static/description/odoo_python_libs.png
odoo/addons/github_connector_odoo/static/description/reporting_module_by_serie.png
odoo/addons/github_connector_odoo/static/src/img/default_image_module.png
odoo/addons/github_connector_odoo/static/src/img/default_image_module_version.png
odoo10_addon_github_connector_odoo-10.0.1.0.0.99.dev5.dist-info/DESCRIPTION.rst
odoo10_addon_github_connector_odoo-10.0.1.0.0.99.dev5.dist-info/METADATA
odoo10_addon_github_connector_odoo-10.0.1.0.0.99.dev5.dist-info/RECORD
odoo10_addon_github_connector_odoo-10.0.1.0.0.99.dev5.dist-info/WHEEL
odoo10_addon_github_connector_odoo-10.0.1.0.0.99.dev5.dist-info/metadata.json
odoo10_addon_github_connector_odoo-10.0.1.0.0.99.dev5.dist-info/namespace_packages.txt
odoo10_addon_github_connector_odoo-10.0.1.0.0.99.dev5.dist-info/top_level.txt
