Metadata-Version: 2.0
Name: odoo10-addon-github-connector-odoo
Version: 10.0.1.0.0.99.dev5
Summary: Analyze Odoo modules information from Github repositories
Home-page: UNKNOWN
Author: Odoo Community Association (OCA), Sylvain LE GAL, GRAP
Author-email: support@odoo-community.org
License: AGPL-3
Platform: UNKNOWN
Classifier: Programming Language :: Python
Classifier: Framework :: Odoo
Classifier: License :: OSI Approved :: GNU Affero General Public License v3
Requires-Python: ~=2.7
Requires-Dist: odoo (<10.1dev,>=10.0)
Requires-Dist: odoo10-addon-github-connector
